mcp_server/README.md
mcp_server/__init__.py
mcp_server/application.py
mcp_server/server.py
mcp_server/config/__init__.py
mcp_server/config/config.py
mcp_server/consts/__init__.py
mcp_server/consts/consts.py
mcp_server/core/__init__.py
mcp_server/core/cdn/__init__.py
mcp_server/core/cdn/cdn.py
mcp_server/core/cdn/tools.py
mcp_server/core/live_streaming/__init__.py
mcp_server/core/live_streaming/live_streaming.py
mcp_server/core/live_streaming/tools.py
mcp_server/core/media_processing/__init__.py
mcp_server/core/media_processing/processing.py
mcp_server/core/media_processing/tools.py
mcp_server/core/media_processing/utils.py
mcp_server/core/storage/__init__.py
mcp_server/core/storage/resource.py
mcp_server/core/storage/storage.py
mcp_server/core/storage/tools.py
mcp_server/core/version/__init__.py
mcp_server/core/version/tools.py
mcp_server/core/version/version.py
mcp_server/resource/__init__.py
mcp_server/resource/resource.py
mcp_server/tools/__init__.py
mcp_server/tools/tools.py
iflow_mcp_qiniu_mcp_server-1.4.1.dist-info/METADATA
iflow_mcp_qiniu_mcp_server-1.4.1.dist-info/WHEEL
iflow_mcp_qiniu_mcp_server-1.4.1.dist-info/entry_points.txt
iflow_mcp_qiniu_mcp_server-1.4.1.dist-info/licenses/LICENSE
iflow_mcp_qiniu_mcp_server-1.4.1.dist-info/RECORD
